Veridu/__init__.py
Veridu/SDK/__init__.py
Veridu/SDK/Session.py
Veridu/SDK/API.py
Veridu/Exceptions/APIError.py
Veridu/Exceptions/__init__.py
Veridu/Exceptions/InvalidUsername.py
Veridu/Exceptions/EmptySession.py
Veridu/Exceptions/InvalidFormat.py
Veridu/Exceptions/InvalidResponse.py
Veridu/Exceptions/NonceMismatch.py
veridu_python-0.1.3.dist-info/DESCRIPTION.rst
veridu_python-0.1.3.dist-info/METADATA
veridu_python-0.1.3.dist-info/metadata.json
veridu_python-0.1.3.dist-info/WHEEL
veridu_python-0.1.3.dist-info/top_level.txt
veridu_python-0.1.3.dist-info/RECORD
