Metadata-Version: 2.0
Name: veridu-python
Version: 0.1.3
Summary: Veridu Python SDK
Home-page: https://github.com/veridu/veridu-python
Author: Veridu Ltd
Author-email: contact@veridu.com
License: MIT
Keywords: veridu,sdk,user identification,social media,online services,single sign on
Platform: UNKNOWN
Classifier: Development Status :: 3 - Alpha
Classifier: Intended Audience :: Developers
Classifier: Topic :: Software Development :: Build Tools
Classifier: License :: OSI Approved :: MIT License
Classifier: Programming Language :: Python :: 2
Classifier: Programming Language :: Python :: 2.6
Classifier: Programming Language :: Python :: 2.7
Classifier: Programming Language :: Python :: 3
Classifier: Programming Language :: Python :: 3.2
Classifier: Programming Language :: Python :: 3.3
Classifier: Programming Language :: Python :: 3.4
Classifier: Programming Language :: Python :: 3.5
Requires-Dist: six (==1.10.0)
